changeforest/plotting.py
changeforest/control.py
changeforest/__init__.py
changeforest/changeforest.cpython-314-darwin.so
changeforest-1.2.1.dist-info/RECORD
changeforest-1.2.1.dist-info/WHEEL
changeforest-1.2.1.dist-info/METADATA
changeforest-1.2.1.dist-info/licenses/LICENSE
