Metadata-Version: 2.4
Name: changeforest
Version: 1.2.1
Classifier: License :: OSI Approved :: BSD License
Classifier: Programming Language :: Python
License-File: LICENSE
Summary: Random Forests for Change Point Detection
Requires-Python: >=3.8
Project-URL: homepage, https://github.com/mlondschien/changeforest/
